{"Berwick-upon-Tweed": {"party_info": {"ukip": {"vote_total": 4785, "vote_percentage": 10.086212347969056, "name": "Nigel Coghill-Marshall", "change_in_percentage": 6.852517402731147}, "conservative": {"vote_total": 16485, "vote_percentage": 34.74842435867709, "name": "Anne-Marie Trevelyan", "change_in_percentage": -1.9746953894953378}, "other": {"vote_total": 675, "vote_percentage": 1.4228199236946946, "name": "Neil Humphrey", "change_in_percentage": ""}, "green": {"vote_total": 2255, "vote_percentage": 4.753272485824498, "name": "Rachael Roberts", "change_in_percentage": 4.753272485824498}, "libdems": {"vote_total": 16486, "vote_percentage": 34.75053224004553, "name": "Julie P\u00f6rksen", "change_in_percentage": -8.970688395246754}, "labour": {"vote_total": 6755, "vote_percentage": 14.238738643789128, "name": "Scott Dickinson", "change_in_percentage": 1.0724231829290645}, "others": {"vote_total": 0, "vote_percentage": 0.0, "name": "Others", "change_in_percentage": ""}}, "seat_info": {"winning_party": "libdems", "declared_at_simple": "02:34", "area": "northeastengland", "majority_percentage": 0.0021078813684365844, "percentage_turnout": 62, "majority_total": 1, "incumbent": "libdems", "electorate": 76469, "declared_at": 1429752857.471, "turnout": 47441, "change": "hold"}}}