{"Reading West": {"party_info": {"ukip": {"vote_total": 2719.0, "vote_percentage": 5.64, "name": "Paul Fisher Test", "change_in_percentage": 2.4672669892699344}, "conservative": {"vote_total": 18791.0, "vote_percentage": 38.95, "name": "Edward Clarke Test", "change_in_percentage": -4.229044813801806}, "labour": {"vote_total": 17334.0, "vote_percentage": 35.93, "name": "Matthew King Test", "change_in_percentage": 5.382977067115505}, "green": {"vote_total": 4184.0, "vote_percentage": 8.67, "name": "Tim Smith Test", "change_in_percentage": 7.445510204081632}, "other2": {"vote_total": 2662.0, "vote_percentage": 5.529999999999999, "name": "Others", "change_in_percentage": 3.7374479276246575}, "libdems": {"vote_total": 2560.0, "vote_percentage": 5.31, "name": "Gavin Hope Test", "change_in_percentage": -14.774157374289924}}, "seat_info": {"winning_party": "conservative", "declared_at_simple": "10:58", "majority_percentage": "3.02", "area": "southeastengland", "percentage_turnout": "66.90", "majority_total": "1457", "incumbent": "conservative", "electorate": 72118, "declared_at": "2015-04-16T10:58:21+01:00", "turnout": "48250", "change": "hold"}}, "West Bromwich East": {"party_info": {"labour": {"vote_total": 11518.0, "vote_percentage": 27.77, "name": "John Stewart Test", "change_in_percentage": -18.7570092226614}, "green": {"vote_total": 2885.0, "vote_percentage": 6.96, "name": "Peter Charlesworth Test", "change_in_percentage": 6.96}, "ukip": {"vote_total": 1875.0, "vote_percentage": 4.52, "name": "Tom Flynn Test", "change_in_percentage": 1.9271146245059283}, "libdems": {"vote_total": 6778.0, "vote_percentage": 16.34, "name": "Nicholas Brown Test", "change_in_percentage": 3.1832147562582342}, "conservative": {"vote_total": 18413.0, "vote_percentage": 44.4, "name": "Ruth Williams Test", "change_in_percentage": 15.517259552042159}}, "seat_info": {"winning_party": "conservative", "declared_at_simple": "10:57", "majority_percentage": "16.63", "area": "westmidlands", "percentage_turnout": "66.01", "majority_total": "6895", "incumbent": "labour", "electorate": 62824, "declared_at": "2015-04-16T10:57:22+01:00", "turnout": "41469", "change": "gain"}}, "Sheffield Heeley": {"party_info": {"ukip": {"vote_total": 535.0, "vote_percentage": 1.12, "name": "Jeff Fox Test", "change_in_percentage": -2.62348560103741}, "conservative": {"vote_total": 18272.0, "vote_percentage": 38.09, "name": "Clive Wilkins Test", "change_in_percentage": 20.76475716278046}, "labour": {"vote_total": 25733.0, "vote_percentage": 53.64, "name": "Mike Harris Test", "change_in_percentage": 11.045005994470408}, "green": {"vote_total": 823.0, "vote_percentage": 1.72, "name": "Simon Cooper Test", "change_in_percentage": -0.6998086662915026}, "other2": {"vote_total": 574.0, "vote_percentage": 1.2, "name": "Others", "change_in_percentage": -4.329593110029116}, "libdems": {"vote_total": 2034.0, "vote_percentage": 4.24, "name": "Martin Jones Test", "change_in_percentage": -24.14687577989283}}, "seat_info": {"winning_party": "labour", "declared_at_simple": "10:52", "majority_percentage": "15.55", "area": "yorkshireandthehumber", "percentage_turnout": "72.83", "majority_total": "7461", "incumbent": "labour", "electorate": 65869, "declared_at": "2015-04-16T10:52:52+01:00", "turnout": "47971", "change": "hold"}}, "Wakefield": {"party_info": {"ukip": {"vote_total": 3968.0, "vote_percentage": 8.26, "name": "Margaret Young Test", "change_in_percentage": 8.26}, "conservative": {"vote_total": 12475.0, "vote_percentage": 25.98, "name": "Michael Cooper Test", "change_in_percentage": -9.662606426064261}, "labour": {"vote_total": 18096.0, "vote_percentage": 37.69, "name": "David Young Test", "change_in_percentage": -1.5818927189271932}, "green": {"vote_total": 6105.0, "vote_percentage": 12.72, "name": "Mohammed Webb Test", "change_in_percentage": 10.755730357303573}, "other2": {"vote_total": 3255.0, "vote_percentage": 6.78, "name": "Others", "change_in_percentage": -0.015067950679506836}, "libdems": {"vote_total": 4112.0, "vote_percentage": 8.56, "name": "Simon Griffiths Test", "change_in_percentage": -7.766163261632615}}, "seat_info": {"winning_party": "labour", "declared_at_simple": "10:55", "majority_percentage": "11.71", "area": "yorkshireandthehumber", "percentage_turnout": "67.78", "majority_total": "5621", "incumbent": "labour", "electorate": 70834, "declared_at": "2015-04-16T10:55:36+01:00", "turnout": "48011", "change": "hold"}}, "Erewash": {"party_info": {"labour": {"vote_total": 10498.0, "vote_percentage": 21.86, "name": "Michael Davies Test", "change_in_percentage": -12.361905041769866}, "green": {"vote_total": 4686.0, "vote_percentage": 9.76, "name": "Ann Sheppard Test", "change_in_percentage": 8.63914025439738}, "ukip": {"vote_total": 3046.0, "vote_percentage": 6.34, "name": "Howard Gray Test", "change_in_percentage": 4.545365014063221}, "libdems": {"vote_total": 9698.0, "vote_percentage": 20.2, "name": "George Love Test", "change_in_percentage": 2.6881407161748037}, "conservative": {"vote_total": 20088.0, "vote_percentage": 41.84, "name": "Andrew Murphy Test", "change_in_percentage": 2.3685252508291015}}, "seat_info": {"winning_party": "conservative", "declared_at_simple": "10:54", "majority_percentage": "19.97", "area": "eastmidlands", "percentage_turnout": "68.94", "majority_total": "9590", "incumbent": "conservative", "electorate": 69654, "declared_at": "2015-04-16T10:54:36+01:00", "turnout": "48016", "change": "hold"}}, "Fermanagh and South Tyrone": {"party_info": {"uu": {"vote_total": 1660.0, "vote_percentage": 3.72, "name": "Simon White Test", "change_in_percentage": 3.72}, "alliance": {"vote_total": 1079.0, "vote_percentage": 2.42, "name": "John Smith Test", "change_in_percentage": 1.486299168856697}, "green": {"vote_total": 21692.0, "vote_percentage": 48.57, "name": "Frank Jones Test", "change_in_percentage": 48.57}, "sdlp": {"vote_total": 15350.0, "vote_percentage": 34.37, "name": "Keith Holden Test", "change_in_percentage": 26.73373736726278}, "sinnfein": {"vote_total": 4881.0, "vote_percentage": 10.93, "name": "Christopher Arnott Test", "change_in_percentage": -34.58844967202957}}, "seat_info": {"winning_party": "green", "declared_at_simple": "10:56", "majority_percentage": "14.20", "area": "northernireland", "percentage_turnout": "65.77", "majority_total": "6342", "incumbent": "sinnfein", "electorate": 67908, "declared_at": "2015-04-16T10:56:36+01:00", "turnout": "44662", "change": "gain"}}, "Central Suffolk and North Ipswich": {"party_info": {"ukip": {"vote_total": 485.0, "vote_percentage": 1.08, "name": "Jonathan Jones Test", "change_in_percentage": -3.339692998876825}, "conservative": {"vote_total": 19474.0, "vote_percentage": 43.44, "name": "Jo Stewart Test", "change_in_percentage": -7.336862598277804}, "labour": {"vote_total": 21326.0, "vote_percentage": 47.58, "name": "Thomas Phillips Test", "change_in_percentage": 31.41377012354923}, "green": {"vote_total": 746.0, "vote_percentage": 1.66, "name": "Mike Jenkins Test", "change_in_percentage": -1.0580831149382253}, "other2": {"vote_total": 315.0, "vote_percentage": 0.7, "name": "Others", "change_in_percentage": -0.24908274054661184}, "libdems": {"vote_total": 2480.0, "vote_percentage": 5.53, "name": "Clare Hutton Test", "change_in_percentage": -19.44004867090977}}, "seat_info": {"winning_party": "labour", "declared_at_simple": "10:53", "majority_percentage": "4.13", "area": "eastofengland", "percentage_turnout": "59.10", "majority_total": "1852", "incumbent": "conservative", "electorate": 75848, "declared_at": "2015-04-16T10:53:41+01:00", "turnout": "44826", "change": "gain"}}, "Lewisham West and Penge": {"party_info": {"ukip": {"vote_total": 875.0, "vote_percentage": 2.05, "name": "Andrew Webb Test", "change_in_percentage": -0.43067868881584825}, "conservative": {"vote_total": 24366.0, "vote_percentage": 57.18, "name": "Peter Henderson Test", "change_in_percentage": 31.664765035089278}, "labour": {"vote_total": 11955.0, "vote_percentage": 28.05, "name": "Colin Peacock Test", "change_in_percentage": -13.037767611264105}, "green": {"vote_total": 1347.0, "vote_percentage": 3.16, "name": "Tim Bennett Test", "change_in_percentage": 1.0923976192591276}, "other2": {"vote_total": 1179.0, "vote_percentage": 2.77, "name": "Others", "change_in_percentage": 2.065993603979746}, "libdems": {"vote_total": 2892.0, "vote_percentage": 6.79, "name": "David Dhillon Test", "change_in_percentage": -21.3547099582482}}, "seat_info": {"winning_party": "conservative", "declared_at_simple": "10:57", "majority_percentage": "29.12", "area": "london", "percentage_turnout": "61.74", "majority_total": "12411", "incumbent": "labour", "electorate": 69022, "declared_at": "2015-04-16T10:57:52+01:00", "turnout": "42614", "change": "gain"}}}